{
  "db_name": "PostgreSQL",
  "query": "\n            SELECT \n                id, service, access_token, refresh_token, token_type, \n                expires_at, scope, created_at, updated_at\n            FROM oauth_tokens\n            WHERE service = $1\n            ",
  "describe": {
    "columns": [
      {
        "ordinal": 0,
        "name": "id",
        "type_info": "Uuid"
      },
      {
        "ordinal": 1,
        "name": "service",
        "type_info": "Varchar"
      },
      {
        "ordinal": 2,
        "name": "access_token",
        "type_info": "Text"
      },
      {
        "ordinal": 3,
        "name": "refresh_token",
        "type_info": "Text"
      },
      {
        "ordinal": 4,
        "name": "token_type",
        "type_info": "Varchar"
      },
      {
        "ordinal": 5,
        "name": "expires_at",
        "type_info": "Timestamptz"
      },
      {
        "ordinal": 6,
        "name": "scope",
        "type_info": "Text"
      },
      {
        "ordinal": 7,
        "name": "created_at",
        "type_info": "Timestamptz"
      },
      {
        "ordinal": 8,
        "name": "updated_at",
        "type_info": "Timestamptz"
      }
    ],
    "parameters": {
      "Left": [
        "Text"
      ]
    },
    "nullable": [
      false,
      false,
      false,
      true,
      true,
      false,
      true,
      true,
      true
    ]
  },
  "hash": "d6acc181c315d70e381e0e6f6f4560f917d6fb72bc746448473ba3362bf976c6"
}
